{
  "product": {
    "name": "[SALE] Áo polo thể thao nam YODY phối nẹp in chữ, vải thun chạm mát, thấm hút, co giãn SAM7150",
    "price": "",
    "sold": "245",
    "rating": "4.9",
    "num_ratings": "75",
    "sizes": [
      "M",
      "L",
      "XL",
      "2XL",
      "3XL"
    ],
    "colors": [
      "COBAN",
      "Đen",
      "Trắng"
    ],
    "stock_available": "",
    "categories": [
      "Shopee",
      "Thời Trang Nam",
      "Áo",
      "Áo Polo",
      "Shopee",
      "Thời Trang Nam",
      "Áo",
      "Áo Polo"
    ]
  },
  "ratings": [
    {
      "author": "muquyn166",
      "date": "2025-05-18 12:58",
      "variant": "Đen,M",
      "stars": 5,
      "comment": "Áo rất đẹp,sẽ ủng hộ shop tiếp, mình mua sản phẩm của yody nhiều rồi chất mặc rất mát không có gì phải chê,phom dáng chuẩn , giao hàng nhanh,trước mình mua tại cửa hàng nguyên mác là 379k",
      "chất liệu": "",
      "màu sắc": "Đen",
      "đúng với mô tả": "đúng",
      "images": [
        "https://down-vn.img.susercontent.com/file/vn-11134103-7ra0g-m9wn9043ocw4f3"
      ],
      "videos": [
        "https://down-tx-sg.vod.susercontent.com/api/v4/11110103/mms/vn-11110103-6khw4-m9wn6zc09daa23.default.mp4"
      ]
    },
    {
      "author": "rn1oyiols_",
      "date": "2025-04-20 07:44",
      "variant": "COBAN,L",
      "stars": 5,
      "comment": "Giao đúng màu, chất mát, mịn, mặc vừa người. Mình định mua thêm cái đen",
      "chất liệu": "thun mát",
      "màu sắc": "xanh",
      "đúng với mô tả": "dáng vừa người. Mặc ôm",
      "images": [
        "https://down-vn.img.susercontent.com/file/vn-11134103-7ra0g-m8sdgirv8ltu0e"
      ],
      "videos": [
        "https://down-ws-sg.vod.susercontent.com/api/v4/11110103/mms/vn-11110103-6khwf-m8sdh5gq16yv13.default.mp4"
      ]
    },
    {
      "author": "gzsjijg2n2",
      "date": "2025-04-24 21:54",
      "variant": "Đen,3XL",
      "stars": 5,
      "comment": "Chất liêu màu sắc giống mẫu.giao hàng nhanh.hàng YODY thì ko cần phải nói nhiều điểm 10 ko có nhưng ạ",
      "chất liệu": "đúng",
      "màu sắc": "đen",
      "đúng với mô tả": "đúng",
      "images": [
        "https://down-vn.img.susercontent.com/file/vn-11134103-7ra0g-m8yx4jbfhcav84",
        "https://down-vn.img.susercontent.com/file/vn-11134103-7ra0g-m8yx4jbfiqvbbc",
        "https://down-vn.img.susercontent.com/file/vn-11134103-7ra0g-m8yx4jbfk5fra5",
        "https://down-vn.img.susercontent.com/file/vn-11134103-7ra0g-m8yx4jbflk073e",
        "https://down-vn.img.susercontent.com/file/vn-11134103-7ra0g-m8yx4jbfmykn35"
      ],
      "videos": [
        "https://down-ws-sg.vod.susercontent.com/api/v4/11110103/mms/vn-11110103-6khw6-m8yx9800k2v64b.16000051745506297.mp4"
      ]
    },
    {
      "author": "boongbin90",
      "date": "2025-04-24 23:13",
      "variant": "COBAN,XL",
      "stars": 5,
      "comment": "Áo chất lượng vải mát lắm cảm giác thoáng mát dễ chịu ,shop tự vấn nhiệt tình , đóng gói cẩn thận,giao hàng nhanh chóng cám ơn shop sẽ ủng hộ lần sau",
      "chất liệu": "mát",
      "màu sắc": "xanh coban",
      "đúng với mô tả": "",
      "images": [],
      "videos": []
    },
    {
      "author": "m*****3",
      "date": "2025-04-26 12:27",
      "variant": "Đen,3XL",
      "stars": 5,
      "comment": "Yody tinh tế, che giá sản phẩm khi gửi. \nMàu áo đẹp lắm, vải mềm và mát",
      "chất liệu": "",
      "màu sắc": "",
      "đúng với mô tả": "",
      "images": [
        "https://down-vn.img.susercontent.com/file/vn-11134103-7ra0g-m917og6g5taab2",
        "https://down-vn.img.susercontent.com/file/vn-11134103-7ra0g-m917og6gcu4ie7"
      ],
      "videos": [
        "https://down-tx-sg.vod.susercontent.com/api/v4/11110103/mms/vn-11110103-6khw0-m917o5k3pbwi96.16000051745644876.mp4"
      ]
    },
    {
      "author": "g2a7jg_89f",
      "date": "2025-04-25 10:00",
      "variant": "Trắng,3XL",
      "stars": 5,
      "comment": "Áo đứng form, chất vải mềm, nhẹ, hút mồ hôi tốt, mua trên live được giá sale chỉ 161k, sẽ mua thêm các sản phẩm khác của shop",
      "chất liệu": "",
      "màu sắc": "",
      "đúng với mô tả": "",
      "images": [],
      "videos": []
    },
    {
      "author": "n*****t",
      "date": "2025-05-08 16:44",
      "variant": "COBAN,XL",
      "stars": 5,
      "comment": "Sản phẩm chất lượng, săn sale giá rẻ. Sẽ ủng hộ tiếp khi có nhu cầu",
      "chất liệu": "ok",
      "màu sắc": "ok",
      "đúng với mô tả": "ok",
      "images": [
        "https://down-vn.img.susercontent.com/file/vn-11134103-7ra0g-m9ilndw0qmbra3"
      ],
      "videos": [
        "https://down-ws-sg.vod.susercontent.com/api/v4/11110103/mms/vn-11110103-6khwi-m9ilm6pe0g3r58.default.mp4"
      ]
    },
    {
      "author": "d*****d",
      "date": "2025-04-27 08:22",
      "variant": "COBAN,XL",
      "stars": 5,
      "comment": "Đóng gói cẩn thận,giao hàng nhanh",
      "chất liệu": "không biết",
      "màu sắc": "màu xanh",
      "đúng với mô tả": "đúng với mô tả",
      "images": [],
      "videos": []
    },
    {
      "author": "tranglam1992",
      "date": "2025-05-14 19:05",
      "variant": "Đen,2XL",
      "stars": 5,
      "comment": "Áo đẹp, chất lượng sản phẩm tuyệt vời. Hình ảnh mang tính chất minh họa",
      "chất liệu": "",
      "màu sắc": "",
      "đúng với mô tả": "",
      "images": [
        "https://down-vn.img.susercontent.com/file/vn-11134103-7ra0g-m9ray0cidcoe16"
      ],
      "videos": [
        "https://down-ws-sg.vod.susercontent.com/api/v4/11110103/mms/vn-11110103-6khw9-m9ray68rpbtme8.default.mp4"
      ]
    },
    {
      "author": "n*****8",
      "date": "2025-05-16 14:44",
      "variant": "COBAN,M",
      "stars": 5,
      "comment": "Sản phẩm đẹp k chỉ thừa, giao hàng nhanh, uy tín. Mua yody nhiều làn rồi",
      "chất liệu": "ok",
      "màu sắc": "",
      "đúng với mô tả": "ok",
      "images": [],
      "videos": []
    },
    {
      "author": "m*****h",
      "date": "2025-05-18 03:59",
      "variant": "Đen,2XL",
      "stars": 5,
      "comment": "Hàng đúng mô tả, chất đẹp mặc mềm mát. Đã mua rất nhiều lần",
      "chất liệu": "thun",
      "màu sắc": "đen",
      "đúng với mô tả": "đúng",
      "images": [],
      "videos": []
    },
    {
      "author": "duynk342",
      "date": "2025-05-08 15:19",
      "variant": "COBAN,2XL",
      "stars": 5,
      "comment": "10d yody chất lượng vải tốt",
      "chất liệu": "coton",
      "màu sắc": "xanh",
      "đúng với mô tả": "đẹp",
      "images": [],
      "videos": []
    },
    {
      "author": "shop_matna_dailoan_xachtay",
      "date": "2025-05-04 22:44",
      "variant": "COBAN,2XL",
      "stars": 5,
      "comment": "Áo mặc mát",
      "chất liệu": "thun mát",
      "màu sắc": "xanh",
      "đúng với mô tả": "ok",
      "images": [],
      "videos": []
    },
    {
      "author": "l*****g",
      "date": "2025-04-17 22:49",
      "variant": "COBAN,L",
      "stars": 5,
      "comment": "Áo đẹp, vải mát, chồng mình cao m69 nặng 64 kg mặc L vừa fit, màu xanh dành ai da trắng mặc khá đẹp",
      "chất liệu": "",
      "màu sắc": "",
      "đúng với mô tả": "",
      "images": [],
      "videos": []
    },
    {
      "author": "tungbinh959",
      "date": "2025-05-17 19:29",
      "variant": "COBAN,3XL",
      "stars": 5,
      "comment": "Áo mát nên mua nhá. Sale đc rẻ 161k",
      "chất liệu": "",
      "màu sắc": "",
      "đúng với mô tả": "",
      "images": [
        "https://down-vn.img.susercontent.com/file/vn-11134103-7ra0g-m9v6238cm16q37"
      ],
      "videos": [
        "https://down-zl-sg.vod.susercontent.com/api/v4/11110103/mms/vn-11110103-6khwj-m9vlxybzq4w4fc.16000051747484908.mp4"
      ]
    },
    {
      "author": "tothaolinhdan",
      "date": "2025-05-11 21:10",
      "variant": "COBAN,2XL",
      "stars": 5,
      "comment": "Đẹp. Đúng mô tả. Chất liệu mát. Màu sắc y hình.",
      "chất liệu": "",
      "màu sắc": "",
      "đúng với mô tả": "",
      "images": [],
      "videos": []
    },
    {
      "author": "thuaniupa",
      "date": "2025-05-14 19:28",
      "variant": "Đen,3XL",
      "stars": 5,
      "comment": "Chất mát\nHàng yody châtd lượng khỏi bàn r \nĐồ đẹp ưu đãi nha nên mua nha",
      "chất liệu": "",
      "màu sắc": "",
      "đúng với mô tả": "",
      "images": [],
      "videos": [
        "https://down-zl-sg.vod.susercontent.com/api/v4/11110103/mms/vn-11110103-6khwd-m9rbnhheg7eq61.16000101747225682.mp4"
      ]
    },
    {
      "author": "trinhlinhtlkc",
      "date": "2025-05-07 21:00",
      "variant": "COBAN,M",
      "stars": 5,
      "comment": "Nên mua nhé ok lắm",
      "chất liệu": "ok",
      "màu sắc": "ok",
      "đúng với mô tả": "ok",
      "images": [],
      "videos": []
    },
    {
      "author": "m*****0",
      "date": "2025-04-27 21:51",
      "variant": "COBAN,XL",
      "stars": 5,
      "comment": "Chất liệu vải mát, màu xanh coban đẹp. Hình ảnh mang tính chất nhận xu",
      "chất liệu": "",
      "màu sắc": "",
      "đúng với mô tả": "",
      "images": [],
      "videos": []
    },
    {
      "author": "yentran9194",
      "date": "2025-04-17 19:16",
      "variant": "Trắng,3XL",
      "stars": 4,
      "comment": "",
      "chất liệu": "ổn",
      "màu sắc": "1c màu xanh có vẻ hơi phai màu chút",
      "đúng với mô tả": "",
      "images": [],
      "videos": []
    },
    {
      "author": "pminhtri81110",
      "date": "2025-05-23 09:09",
      "variant": "Đen,XL",
      "stars": 5,
      "comment": "",
      "chất liệu": "mát",
      "màu sắc": "đẹp",
      "đúng với mô tả": "đúng",
      "images": [],
      "videos": []
    },
    {
      "author": "pminhtri81110",
      "date": "2025-05-23 09:09",
      "variant": "COBAN,XL",
      "stars": 5,
      "comment": "",
      "chất liệu": "mát",
      "màu sắc": "tốt",
      "đúng với mô tả": "đúng",
      "images": [],
      "videos": []
    },
    {
      "author": "tranvan351",
      "date": "2025-04-17 22:27",
      "variant": "Đen,XL",
      "stars": 5,
      "comment": "chất mềm đẹp lần sau ủng hộ tiếp ạ",
      "chất liệu": "",
      "màu sắc": "",
      "đúng với mô tả": "",
      "images": [],
      "videos": []
    },
    {
      "author": "duongthao_1110",
      "date": "2025-05-13 19:15",
      "variant": "COBAN,2XL",
      "stars": 5,
      "comment": "Nên tăng 1 size so vs bảng size",
      "chất liệu": "",
      "màu sắc": "",
      "đúng với mô tả": "",
      "images": [],
      "videos": []
    },
    {
      "author": "n*****l",
      "date": "2025-04-18 10:22",
      "variant": "Đen,XL",
      "stars": 5,
      "comment": "",
      "chất liệu": "",
      "màu sắc": "Dimao Pro Oral Spray D3 + K2 là sản phẩm bổ sung vitamin K2 và D3 dưới dạng xịt vượt trội, tiện lợi và dễ sử dụng. Sản phẩm đảm bảo mỗi nhát xịt chứa 400IU vitamin D3 và 18,75mcg vitamin K2 theo chuẩn khuyến cáo của Tổ chức Y tế Thế giới WHO và được hấp thu nhanh qua niêm mạc miệng.",
      "đúng với mô tả": "",
      "images": [],
      "videos": []
    },
    {
      "author": "nhando1981",
      "date": "2025-05-04 07:47",
      "variant": "Trắng,M",
      "stars": 5,
      "comment": "Màu trắng màu đục ko đẹp lắm",
      "chất liệu": "",
      "màu sắc": "",
      "đúng với mô tả": "",
      "images": [],
      "videos": []
    },
    {
      "author": "n*****0",
      "date": "2025-05-16 05:29",
      "variant": "Đen,XL",
      "stars": 5,
      "comment": "Không chúc em giàu có, chỉ chúc em bình yên.\nKhông chúc em lộng lẫy, chỉ chúc em không muộn phiền.",
      "chất liệu": "",
      "màu sắc": "",
      "đúng với mô tả": "",
      "images": [],
      "videos": []
    },
    {
      "author": "d*****d",
      "date": "2025-04-21 15:47",
      "variant": "COBAN,2XL",
      "stars": 5,
      "comment": "Giao hàng nhanh, đóng gói cẩn thận",
      "chất liệu": "không biết",
      "màu sắc": "màu xanh coban",
      "đúng với mô tả": "đúng với mô tả",
      "images": [
        "https://down-vn.img.susercontent.com/file/vn-11134103-7ra0g-m8ua2nbqxawy62"
      ],
      "videos": [
        "https://down-zl-sg.vod.susercontent.com/api/v4/11110103/mms/vn-11110103-6khwc-m8ua2xnjt7r6be.16000051745225190.mp4"
      ]
    },
    {
      "author": "tuantute123",
      "date": "2025-04-14 18:18",
      "variant": "Đen,2XL",
      "stars": 5,
      "comment": "(TB) Bạn muốn nhận tin nhắn thoại từ người thân và bạn bè khi điện thoại đang bận hoặc ngoài vùng phủ sóng. Soạn ON gửi 1085 để sử dụng MIỄN PHÍ tiện ích Lời nhắn thoại của VinaPhone. CSKH: 18001091 (0đ).",
      "chất liệu": "",
      "màu sắc": "",
      "đúng với mô tả": "",
      "images": [
        "https://down-vn.img.susercontent.com/file/vn-11134103-7ra0g-m8kfsy88m3k712"
      ],
      "videos": [
        "https://down-zl-sg.vod.susercontent.com/api/v4/11110103/mms/vn-11110103-6khwh-m8kfsn7qrrk4e5.default.mp4"
      ]
    },
    {
      "author": "m*****1",
      "date": "2025-04-16 17:44",
      "variant": "Đen,XL",
      "stars": 5,
      "comment": "Áo chất mềm mịn, có vẻ thoáng khí. Co giãn tốt. Độ bền thì pải chờ thử. Mua đc giá tốt",
      "chất liệu": "",
      "màu sắc": "",
      "đúng với mô tả": "",
      "images": [
        "https://down-vn.img.susercontent.com/file/vn-11134103-7ra0g-m8n9d6iieu6c25"
      ],
      "videos": [
        "https://down-zl-sg.vod.susercontent.com/api/v4/11110103/mms/vn-11110103-6khw5-m8n9df6dqgle92.16000051744800257.mp4"
      ]
    },
    {
      "author": "rml8w2b74x",
      "date": "2025-05-17 12:47",
      "variant": "Đen,3XL",
      "stars": 4,
      "comment": "Form hơi bó",
      "chất liệu": "",
      "màu sắc": "",
      "đúng với mô tả": "",
      "images": [],
      "videos": []
    },
    {
      "author": "lehuong6868",
      "date": "2025-04-16 19:48",
      "variant": "Đen,L",
      "stars": 5,
      "comment": "Áo đẹp, mỏng, mát săn 165 k cũng ok,",
      "chất liệu": "",
      "màu sắc": "",
      "đúng với mô tả": "",
      "images": [],
      "videos": [
        "https://down-ws-sg.vod.susercontent.com/api/v4/11110103/mms/vn-11110103-6khw8-m8ndsp40tdvm19.default.mp4"
      ]
    },
    {
      "author": "lanbichip",
      "date": "2025-04-24 05:52",
      "variant": "Trắng,2XL",
      "stars": 5,
      "comment": "",
      "chất liệu": "",
      "màu sắc": "",
      "đúng với mô tả": "",
      "images": [],
      "videos": []
    },
    {
      "author": "diep08184",
      "date": "2025-04-25 22:06",
      "variant": "COBAN,L",
      "stars": 5,
      "comment": "",
      "chất liệu": "",
      "màu sắc": "",
      "đúng với mô tả": "",
      "images": [],
      "videos": []
    },
    {
      "author": "thutuyen27_09",
      "date": "2025-04-21 19:30",
      "variant": "COBAN,XL",
      "stars": 5,
      "comment": "",
      "chất liệu": "",
      "màu sắc": "",
      "đúng với mô tả": "",
      "images": [],
      "videos": []
    },
    {
      "author": "hoangnoi89",
      "date": "2025-04-28 14:11",
      "variant": "COBAN,M",
      "stars": 5,
      "comment": "",
      "chất liệu": "",
      "màu sắc": "",
      "đúng với mô tả": "",
      "images": [],
      "videos": []
    },
    {
      "author": "huychuong1984",
      "date": "2025-04-17 17:00",
      "variant": "Đen,XL",
      "stars": 5,
      "comment": "",
      "chất liệu": "",
      "màu sắc": "",
      "đúng với mô tả": "",
      "images": [],
      "videos": []
    },
    {
      "author": "anh29",
      "date": "2025-04-18 11:52",
      "variant": "COBAN,2XL",
      "stars": 4,
      "comment": "",
      "chất liệu": "",
      "màu sắc": "",
      "đúng với mô tả": "",
      "images": [],
      "videos": []
    },
    {
      "author": "honganh273",
      "date": "2025-05-05 12:59",
      "variant": "Đen,XL",
      "stars": 5,
      "comment": "",
      "chất liệu": "",
      "màu sắc": "",
      "đúng với mô tả": "",
      "images": [],
      "videos": []
    },
    {
      "author": "thuyjin150989",
      "date": "2025-05-08 06:18",
      "variant": "Trắng,3XL",
      "stars": 5,
      "comment": "",
      "chất liệu": "",
      "màu sắc": "",
      "đúng với mô tả": "",
      "images": [],
      "videos": []
    },
    {
      "author": "thuyjin150989",
      "date": "2025-05-22 09:51",
      "variant": "Trắng,2XL",
      "stars": 5,
      "comment": "",
      "chất liệu": "",
      "màu sắc": "",
      "đúng với mô tả": "",
      "images": [],
      "videos": []
    },
    {
      "author": "thuyjin150989",
      "date": "2025-05-21 11:47",
      "variant": "Đen,3XL",
      "stars": 5,
      "comment": "",
      "chất liệu": "",
      "màu sắc": "",
      "đúng với mô tả": "",
      "images": [],
      "videos": []
    },
    {
      "author": "thuylinh_230295",
      "date": "2025-05-22 18:17",
      "variant": "Đen,M",
      "stars": 5,
      "comment": "",
      "chất liệu": "",
      "màu sắc": "",
      "đúng với mô tả": "",
      "images": [],
      "videos": []
    },
    {
      "author": "phamtrangthammy",
      "date": "2025-04-19 23:08",
      "variant": "COBAN,M",
      "stars": 5,
      "comment": "",
      "chất liệu": "",
      "màu sắc": "",
      "đúng với mô tả": "",
      "images": [],
      "videos": []
    },
    {
      "author": "tranthutrang21984",
      "date": "2025-05-17 17:13",
      "variant": "COBAN,3XL",
      "stars": 5,
      "comment": "",
      "chất liệu": "",
      "màu sắc": "",
      "đúng với mô tả": "",
      "images": [],
      "videos": []
    },
    {
      "author": "anhduy4247",
      "date": "2025-04-18 12:06",
      "variant": "COBAN,3XL",
      "stars": 5,
      "comment": "",
      "chất liệu": "",
      "màu sắc": "",
      "đúng với mô tả": "",
      "images": [],
      "videos": []
    },
    {
      "author": "lephanhoaian",
      "date": "2025-04-18 18:35",
      "variant": "Đen,XL",
      "stars": 5,
      "comment": "",
      "chất liệu": "",
      "màu sắc": "",
      "đúng với mô tả": "",
      "images": [],
      "videos": []
    },
    {
      "author": "lephanhoaian",
      "date": "2025-04-11 21:52",
      "variant": "Đen,L",
      "stars": 5,
      "comment": "",
      "chất liệu": "",
      "màu sắc": "",
      "đúng với mô tả": "",
      "images": [],
      "videos": []
    },
    {
      "author": "tiepthile94",
      "date": "2025-04-22 12:31",
      "variant": "COBAN,XL",
      "stars": 5,
      "comment": "",
      "chất liệu": "",
      "màu sắc": "",
      "đúng với mô tả": "",
      "images": [],
      "videos": []
    },
    {
      "author": "nga4687",
      "date": "2025-05-12 18:02",
      "variant": "COBAN,3XL",
      "stars": 5,
      "comment": "",
      "chất liệu": "",
      "màu sắc": "",
      "đúng với mô tả": "",
      "images": [],
      "videos": []
    },
    {
      "author": "namphong7979",
      "date": "2025-05-20 17:49",
      "variant": "Đen,3XL",
      "stars": 5,
      "comment": "",
      "chất liệu": "",
      "màu sắc": "",
      "đúng với mô tả": "",
      "images": [],
      "videos": []
    },
    {
      "author": "nguyenluong0987",
      "date": "2025-05-21 20:15",
      "variant": "Đen,3XL",
      "stars": 5,
      "comment": "",
      "chất liệu": "",
      "màu sắc": "",
      "đúng với mô tả": "",
      "images": [],
      "videos": []
    },
    {
      "author": "crqahfhx3k",
      "date": "2025-05-14 17:04",
      "variant": "Đen,3XL",
      "stars": 5,
      "comment": "",
      "chất liệu": "",
      "màu sắc": "",
      "đúng với mô tả": "",
      "images": [],
      "videos": []
    },
    {
      "author": "nc52jba13i",
      "date": "2025-04-17 20:05",
      "variant": "Đen,L",
      "stars": 5,
      "comment": "",
      "chất liệu": "",
      "màu sắc": "",
      "đúng với mô tả": "",
      "images": [],
      "videos": []
    },
    {
      "author": "s746gweq79",
      "date": "2025-04-24 21:23",
      "variant": "COBAN,2XL",
      "stars": 5,
      "comment": "",
      "chất liệu": "",
      "màu sắc": "",
      "đúng với mô tả": "",
      "images": [],
      "videos": []
    },
    {
      "author": "s746gweq79",
      "date": "2025-04-24 21:24",
      "variant": "COBAN,2XL",
      "stars": 5,
      "comment": "",
      "chất liệu": "",
      "màu sắc": "",
      "đúng với mô tả": "",
      "images": [],
      "videos": []
    },
    {
      "author": "minhmui",
      "date": "2025-04-25 04:31",
      "variant": "COBAN,2XL",
      "stars": 5,
      "comment": "",
      "chất liệu": "",
      "màu sắc": "",
      "đúng với mô tả": "",
      "images": [],
      "videos": []
    },
    {
      "author": "9*****o",
      "date": "2025-04-16 15:19",
      "variant": "Đen,2XL",
      "stars": 5,
      "comment": "",
      "chất liệu": "",
      "màu sắc": "",
      "đúng với mô tả": "",
      "images": [],
      "videos": []
    },
    {
      "author": "damngoc970",
      "date": "2025-04-16 06:47",
      "variant": "COBAN,XL",
      "stars": 5,
      "comment": "",
      "chất liệu": "",
      "màu sắc": "",
      "đúng với mô tả": "",
      "images": [],
      "videos": []
    },
    {
      "author": "dao8886",
      "date": "2025-04-18 11:01",
      "variant": "Trắng,M",
      "stars": 5,
      "comment": "",
      "chất liệu": "",
      "màu sắc": "",
      "đúng với mô tả": "",
      "images": [],
      "videos": []
    },
    {
      "author": "dao8886",
      "date": "2025-04-18 11:01",
      "variant": "Trắng,M",
      "stars": 5,
      "comment": "",
      "chất liệu": "",
      "màu sắc": "",
      "đúng với mô tả": "",
      "images": [],
      "videos": []
    },
    {
      "author": "kfyvqni5yi",
      "date": "2025-04-21 12:54",
      "variant": "Đen,XL",
      "stars": 5,
      "comment": "",
      "chất liệu": "",
      "màu sắc": "",
      "đúng với mô tả": "",
      "images": [],
      "videos": []
    },
    {
      "author": "s746gweq79",
      "date": "2025-04-22 18:57",
      "variant": "COBAN,2XL",
      "stars": 5,
      "comment": "",
      "chất liệu": "",
      "màu sắc": "",
      "đúng với mô tả": "",
      "images": [],
      "videos": []
    },
    {
      "author": "j04sy8vxim",
      "date": "2025-05-04 14:50",
      "variant": "COBAN,2XL",
      "stars": 5,
      "comment": "",
      "chất liệu": "",
      "màu sắc": "",
      "đúng với mô tả": "",
      "images": [],
      "videos": []
    },
    {
      "author": "n7vyfo8n9w",
      "date": "2025-05-05 15:46",
      "variant": "COBAN,2XL",
      "stars": 5,
      "comment": "",
      "chất liệu": "",
      "màu sắc": "",
      "đúng với mô tả": "",
      "images": [],
      "videos": []
    },
    {
      "author": "3mbv0_yjtu",
      "date": "2025-05-08 09:39",
      "variant": "COBAN,M",
      "stars": 5,
      "comment": "",
      "chất liệu": "",
      "màu sắc": "",
      "đúng với mô tả": "",
      "images": [],
      "videos": []
    },
    {
      "author": "a3texfxybe",
      "date": "2025-05-11 21:06",
      "variant": "Đen,3XL",
      "stars": 5,
      "comment": "",
      "chất liệu": "",
      "màu sắc": "",
      "đúng với mô tả": "",
      "images": [],
      "videos": []
    },
    {
      "author": "92qm_yakko",
      "date": "2025-05-12 23:47",
      "variant": "Trắng,2XL",
      "stars": 5,
      "comment": "",
      "chất liệu": "",
      "màu sắc": "",
      "đúng với mô tả": "",
      "images": [],
      "videos": []
    },
    {
      "author": "dinhtham.123",
      "date": "2025-05-10 22:23",
      "variant": "COBAN,L",
      "stars": 5,
      "comment": "",
      "chất liệu": "",
      "màu sắc": "",
      "đúng với mô tả": "",
      "images": [],
      "videos": []
    },
    {
      "author": "canthinga441",
      "date": "2025-05-17 20:52",
      "variant": "COBAN,3XL",
      "stars": 5,
      "comment": "",
      "chất liệu": "",
      "màu sắc": "",
      "đúng với mô tả": "",
      "images": [],
      "videos": []
    },
    {
      "author": "4sd6eemew1",
      "date": "2025-05-21 20:14",
      "variant": "Đen,3XL",
      "stars": 5,
      "comment": "",
      "chất liệu": "",
      "màu sắc": "",
      "đúng với mô tả": "",
      "images": [],
      "videos": []
    },
    {
      "author": "bonbon132007",
      "date": "2025-05-22 18:07",
      "variant": "COBAN,L",
      "stars": 5,
      "comment": "",
      "chất liệu": "",
      "màu sắc": "",
      "đúng với mô tả": "",
      "images": [],
      "videos": []
    },
    {
      "author": "crqahfhx3k",
      "date": "2025-05-05 16:25",
      "variant": "COBAN,XL",
      "stars": 4,
      "comment": "",
      "chất liệu": "",
      "màu sắc": "",
      "đúng với mô tả": "",
      "images": [],
      "videos": []
    },
    {
      "author": "hixnosk83b",
      "date": "2025-04-19 21:16",
      "variant": "Đen,L",
      "stars": 4,
      "comment": "",
      "chất liệu": "",
      "màu sắc": "",
      "đúng với mô tả": "",
      "images": [],
      "videos": []
    },
    {
      "author": "gdxd1vluo0",
      "date": "2025-04-26 10:10",
      "variant": "Đen,M",
      "stars": 5,
      "comment": "",
      "chất liệu": "",
      "màu sắc": "",
      "đúng với mô tả": "",
      "images": [],
      "videos": []
    }
  ]
}